Metadata-Version: 2.1
Name: dynasty
Version: 0.0.2
Summary: A Python class hierarchy analyzer
Home-page: https://github.com/migolan/dynasty
Author: Michal Golan
Author-email: migolan@gmail.com
License: UNKNOWN
Platform: UNKNOWN
License-File: LICENSE
